eb_multi_app/__init__.py
eb_multi_app/helpers.py
eb_multi_app/main.py
eb_multi_app/mainFunctions.py
eb_multi_app/s3.py
EBMultiApp-0.1.0.dist-info/LICENSE
EBMultiApp-0.1.0.dist-info/METADATA
EBMultiApp-0.1.0.dist-info/WHEEL
EBMultiApp-0.1.0.dist-info/entry_points.txt
EBMultiApp-0.1.0.dist-info/top_level.txt
EBMultiApp-0.1.0.dist-info/zip-safe
EBMultiApp-0.1.0.dist-info/RECORD
