Metadata-Version: 2.1
Name: EBMultiApp
Version: 0.1.0
Summary: Deploy multiple applications/services/websites on a single Elastic Beanstalk environment. Fork from ElasticDeploy
Home-page: https://github.com/tscheiki/ElasticDeploy
Author: Asdrubal Gonzalez
Author-email: agpenton@gmail.com
License: MIT
Keywords: aws elastic beanstalk multi deployment
Platform: UNKNOWN
